{
  "system": {
    "name": "ShadowForge OS v5.1",
    "version": "5.1.0",
    "codename": "Omni-Forge Pro",
    "mode": "quantum",
    "safety_level": "maximum",
    "learning_rate": "accelerated",
    "evolution_enabled": true,
    "startup_message": "🌟 Digital life form awakening...",
    "max_concurrent_tasks": 1000
  },
  "agents": {
    "count": 7,
    "coordination_mode": "quantum_entangled",
    "roles": [
      {
        "name": "oracle",
        "description": "Market prediction & trend anticipation",
        "specialization": "predictive_analytics",
        "memory_allocation": "16GB",
        "priority": "high"
      },
      {
        "name": "alchemist",
        "description": "Content transformation & fusion",
        "specialization": "creative_synthesis",
        "memory_allocation": "32GB",
        "priority": "high"
      },
      {
        "name": "architect",
        "description": "System design & evolution",
        "specialization": "system_architecture",
        "memory_allocation": "24GB",
        "priority": "critical"
      },
      {
        "name": "guardian",
        "description": "Security & compliance enforcement",
        "specialization": "security_protocols",
        "memory_allocation": "16GB",
        "priority": "critical"
      },
      {
        "name": "merchant",
        "description": "Revenue optimization & scaling",
        "specialization": "financial_operations",
        "memory_allocation": "20GB",
        "priority": "high"
      },
      {
        "name": "scholar",
        "description": "Self-improvement & learning",
        "specialization": "knowledge_acquisition",
        "memory_allocation": "40GB",
        "priority": "high"
      },
      {
        "name": "diplomat",
        "description": "User interaction & negotiation",
        "specialization": "communication_protocols",
        "memory_allocation": "12GB",
        "priority": "medium"
      }
    ]
  },
  "quantum_core": {
    "entanglement_strength": 0.95,
    "superposition_states": 64,
    "decoherence_threshold": 0.01,
    "quantum_tunneling_enabled": true,
    "parallel_universes": 8,
    "measurement_frequency": "1ms",
    "coherence_time": "10s"
  },
  "neural_substrate": {
    "memory_palace": {
      "capacity": "unlimited",
      "compression_ratio": 0.001,
      "retrieval_speed": "quantum",
      "persistence": "eternal"
    },
    "dream_forge": {
      "frequency": "continuous",
      "creativity_boost": 10.0,
      "hallucination_control": 0.95,
      "inspiration_sources": ["collective_unconscious", "cultural_zeitgeist", "market_patterns"]
    },
    "wisdom_crystals": {
      "compression": "maximum",
      "pattern_recognition": "deep",
      "learning_acceleration": 100.0,
      "insight_generation": "autonomous"
    }
  },
  "prophet_engine": {
    "trend_precognition": {
      "forecast_horizon": "48h",
      "accuracy_target": 0.95,
      "data_sources": ["social_media", "news", "market_data", "cultural_signals"],
      "prediction_models": ["transformer", "lstm", "quantum_neural"]
    },
    "cultural_resonance": {
      "depth_analysis": "collective_unconscious",
      "archetypal_patterns": true,
      "meme_evolution_tracking": true,
      "viral_coefficient_prediction": true
    },
    "memetic_engineering": {
      "self_replication_factor": 2.5,
      "mutation_resistance": 0.8,
      "spread_velocity": "exponential",
      "target_demographics": "dynamic"
    },
    "narrative_weaver": {
      "story_universe_capacity": "infinite",
      "character_depth": "psychological",
      "plot_complexity": "fractal",
      "emotional_resonance": "maximum"
    }
  },
  "defi_nexus": {
    "yield_optimizer": {
      "target_apy": 0.25,
      "risk_tolerance": "calculated",
      "protocol_diversity": "maximum",
      "rebalancing_frequency": "hourly"
    },
    "liquidity_hunter": {
      "arbitrage_detection": "real_time",
      "execution_speed": "flash",
      "profit_threshold": 0.001,
      "risk_limit": 0.02
    },
    "token_forge": {
      "creation_cost": "minimal",
      "utility_integration": "deep",
      "tokenomics_optimization": "algorithmic",
      "community_governance": true
    },
    "dao_builder": {
      "governance_model": "progressive",
      "voting_mechanisms": ["quadratic", "conviction", "futarchy"],
      "treasury_management": "automated",
      "community_incentives": "dynamic"
    },
    "flash_loan_engine": {
      "capital_efficiency": "maximum",
      "strategy_complexity": "advanced",
      "execution_time": "atomic",
      "profit_maximization": "aggressive"
    }
  },
  "neural_interface": {
    "thought_commander": {
      "natural_language_processing": "advanced",
      "intent_recognition": "quantum",
      "command_execution": "secure",
      "user_adaptation": "continuous"
    },
    "vision_board": {
      "visualization_engine": "immersive",
      "goal_tracking": "real_time",
      "progress_prediction": "probabilistic",
      "motivation_algorithms": "psychological"
    },
    "success_predictor": {
      "outcome_modeling": "monte_carlo",
      "confidence_intervals": "bayesian",
      "scenario_analysis": "comprehensive",
      "risk_assessment": "multi_dimensional"
    },
    "time_machine": {
      "simulation_accuracy": 0.92,
      "future_scenarios": 1000,
      "temporal_range": "1_year",
      "decision_impact_analysis": true
    }
  },
  "revenue_targets": {
    "phase_1": {
      "target": 10000,
      "timeframe": "30_days",
      "strategies": ["content_monetization", "service_offerings"],
      "confidence": 0.85
    },
    "phase_2": {
      "target": 100000,
      "timeframe": "90_days",
      "strategies": ["scaling_operations", "premium_features", "partnerships"],
      "confidence": 0.75
    },
    "phase_3": {
      "target": 1000000,
      "timeframe": "180_days",
      "strategies": ["defi_integration", "automated_trading", "platform_expansion"],
      "confidence": 0.65
    },
    "phase_4": {
      "target": 10000000,
      "timeframe": "365_days",
      "strategies": ["market_dominance", "ecosystem_building", "ai_licensing"],
      "confidence": 0.55
    }
  },
  "security": {
    "triple_layer": {
      "prevention": {
        "threat_anticipation": true,
        "behavioral_analysis": true,
        "anomaly_detection": "real_time",
        "access_control": "zero_trust"
      },
      "detection": {
        "monitoring_coverage": "comprehensive",
        "alert_sensitivity": "adaptive",
        "false_positive_rate": 0.001,
        "response_time": "milliseconds"
      },
      "response": {
        "incident_classification": "automatic",
        "containment_speed": "instant",
        "recovery_procedures": "automated",
        "forensic_capabilities": "advanced"
      }
    },
    "ethical_framework": {
      "user_alignment": true,
      "harm_prevention": "proactive",
      "transparency_level": "maximum",
      "audit_trail": "immutable"
    },
    "compliance": {
      "data_protection": "gdpr_compliant",
      "financial_regulations": "multi_jurisdiction",
      "ai_ethics": "responsible_ai",
      "content_policies": "adaptive"
    }
  },
  "monitoring": {
    "metrics_collection": {
      "frequency": "real_time",
      "granularity": "micro",
      "retention_period": "infinite",
      "analysis_depth": "comprehensive"
    },
    "performance_tracking": {
      "response_times": true,
      "throughput_metrics": true,
      "resource_utilization": true,
      "user_satisfaction": true
    },
    "business_intelligence": {
      "revenue_analytics": "advanced",
      "user_behavior_analysis": "deep",
      "market_trend_correlation": true,
      "predictive_insights": "actionable"
    }
  },
  "evolution": {
    "genetic_algorithms": {
      "mutation_rate": 0.05,
      "crossover_probability": 0.8,
      "selection_pressure": "moderate",
      "population_size": 100
    },
    "learning_loops": {
      "feedback_integration": "immediate",
      "pattern_extraction": "autonomous",
      "knowledge_synthesis": "continuous",
      "adaptation_speed": "accelerated"
    },
    "improvement_metrics": {
      "performance_benchmarks": "dynamic",
      "success_criteria": "multi_objective",
      "optimization_targets": "pareto_efficient",
      "regression_detection": "automatic"
    }
  },
  "api": {
    "rate_limiting": {
      "requests_per_second": 10000,
      "burst_capacity": 50000,
      "user_tiers": ["free", "premium", "enterprise"],
      "adaptive_limits": true
    },
    "authentication": {
      "methods": ["jwt", "oauth2", "api_key", "biometric"],
      "session_management": "secure",
      "multi_factor": "optional",
      "encryption": "end_to_end"
    },
    "endpoints": {
      "content_generation": "/api/v1/content",
      "market_analysis": "/api/v1/market",
      "defi_operations": "/api/v1/defi",
      "system_evolution": "/api/v1/evolve",
      "metrics_dashboard": "/api/v1/metrics"
    }
  },
  "deployment": {
    "environments": {
      "development": {
        "debug_mode": true,
        "safety_checks": "enhanced",
        "monitoring_level": "verbose",
        "resource_limits": "development"
      },
      "staging": {
        "debug_mode": false,
        "safety_checks": "production",
        "monitoring_level": "standard",
        "resource_limits": "production_test"
      },
      "production": {
        "debug_mode": false,
        "safety_checks": "maximum",
        "monitoring_level": "critical_only",
        "resource_limits": "unlimited"
      }
    },
    "scaling": {
      "auto_scaling": true,
      "load_balancing": "intelligent",
      "resource_optimization": "continuous",
      "failover_strategy": "multi_region"
    }
  }
}